fuse_cdm
