Metadata-Version: 2.1
Name: fuse-cdm
Version: 1.5.0
Summary: Access fuse common data model library for cellfie analysis suite
Home-page:  
License: MIT
License-File: LICENSE
